[{"type":"Single","lane":5,"time":2.7586206896551726},{"type":"Single","lane":3,"time":4.137931034482759},{"type":"Single","lane":5,"time":5.517241379310345},{"type":"Bar","lane":[2,2],"time":[6.896551724137931,8.965517241379311]},{"type":"Long","lane":2,"time":6.896551724137931},{"type":"Bar","lane":[6,6],"time":[6.896551724137931,8.965517241379311]},{"type":"Long","lane":6,"time":6.896551724137931},{"type":"Sim","lane":[2,6],"time":6.896551724137931},{"type":"Long","lane":2,"time":8.965517241379311},{"type":"Long","lane":6,"time":8.965517241379311},{"type":"Sim","lane":[2,6],"time":8.965517241379311},{"type":"Skill","lane":5,"time":9.482758620689655},{"type":"Single","lane":3,"time":9.482758620689655},{"type":"Sim","lane":[3,5],"time":9.482758620689655},{"type":"Single","lane":2,"time":10.344827586206897},{"type":"Single","lane":5,"time":11.03448275862069},{"type":"Single","lane":2,"time":11.724137931034484},{"type":"Single","lane":6,"time":12.413793103448276},{"type":"Single","lane":3,"time":13.10344827586207},{"type":"Single","lane":6,"time":13.793103448275861},{"type":"Single","lane":3,"time":14.482758620689657},{"type":"Single","lane":2,"time":15.17241379310345},{"type":"Single","lane":5,"time":15.862068965517242},{"type":"Single","lane":2,"time":16.551724137931036},{"type":"Single","lane":5,"time":17.241379310344826},{"type":"Bar","lane":[2,2],"time":[17.75862068965517,20.517241379310345]},{"type":"Long","lane":2,"time":17.75862068965517},{"type":"Bar","lane":[6,6],"time":[17.75862068965517,20.517241379310345]},{"type":"Long","lane":6,"time":17.75862068965517},{"type":"Sim","lane":[2,6],"time":17.75862068965517},{"type":"Long","lane":2,"time":20.517241379310345},{"type":"Long","lane":6,"time":20.517241379310345},{"type":"Sim","lane":[2,6],"time":20.517241379310345},{"type":"Single","lane":5,"time":21.379310344827587},{"type":"Skill","lane":3,"time":22.75862068965517},{"type":"Single","lane":6,"time":24.137931034482758},{"type":"Single","lane":2,"time":25.517241379310345},{"type":"Single","lane":5,"time":26.896551724137932},{"type":"Single","lane":3,"time":28.275862068965516},{"type":"Single","lane":2,"time":28.79310344827586},{"type":"Single","lane":6,"time":28.79310344827586},{"type":"Sim","lane":[2,6],"time":28.79310344827586},{"type":"Single","lane":3,"time":31.03448275862069},{"type":"Single","lane":5,"time":31.03448275862069},{"type":"Sim","lane":[3,5],"time":31.03448275862069},{"type":"Single","lane":6,"time":32.41379310344828},{"type":"Single","lane":2,"time":33.79310344827586},{"type":"Single","lane":5,"time":35.172413793103445},{"type":"Skill","lane":3,"time":36.55172413793104},{"type":"Single","lane":6,"time":37.93103448275862},{"type":"Single","lane":2,"time":39.310344827586206},{"type":"Single","lane":5,"time":40.689655172413794},{"type":"Single","lane":3,"time":41.37931034482759},{"type":"Single","lane":5,"time":42.06896551724138},{"type":"Single","lane":6,"time":42.758620689655174},{"type":"Single","lane":5,"time":44.13793103448276},{"type":"Single","lane":3,"time":45.51724137931034},{"type":"Single","lane":2,"time":46.896551724137936},{"type":"Single","lane":5,"time":48.275862068965516},{"type":"Single","lane":3,"time":49.6551724137931},{"type":"Single","lane":6,"time":51.03448275862069},{"type":"Single","lane":2,"time":52.41379310344828},{"type":"Single","lane":5,"time":53.793103448275865},{"type":"Single","lane":3,"time":54.48275862068966},{"type":"Single","lane":6,"time":55.172413793103445},{"type":"Single","lane":2,"time":55.86206896551724},{"type":"Bar","lane":[3,3],"time":[56.55172413793103,60.51724137931034]},{"type":"Long","lane":3,"time":56.55172413793103},{"type":"Bar","lane":[5,5],"time":[56.55172413793103,60.51724137931034]},{"type":"Long","lane":5,"time":56.55172413793103},{"type":"Sim","lane":[3,5],"time":56.55172413793103},{"type":"Long","lane":3,"time":60.51724137931034},{"type":"Long","lane":5,"time":60.51724137931034},{"type":"Sim","lane":[3,5],"time":60.51724137931034},{"type":"Single","lane":2,"time":61.724137931034484},{"type":"Single","lane":6,"time":61.724137931034484},{"type":"Sim","lane":[2,6],"time":61.724137931034484},{"type":"Single","lane":5,"time":62.06896551724138},{"type":"Single","lane":3,"time":62.75862068965517},{"type":"Single","lane":6,"time":63.44827586206897},{"type":"Single","lane":2,"time":64.13793103448275},{"type":"Skill","lane":5,"time":64.82758620689656},{"type":"Single","lane":3,"time":65.51724137931035},{"type":"Bar","lane":[6,6],"time":[66.20689655172414,66.89655172413794]},{"type":"Long","lane":6,"time":66.20689655172414},{"type":"Long","lane":6,"time":66.89655172413794},{"type":"Bar","lane":[2,2],"time":[67.58620689655172,68.27586206896552]},{"type":"Long","lane":2,"time":67.58620689655172},{"type":"Long","lane":2,"time":68.27586206896552},{"type":"Bar","lane":[6,6],"time":[68.9655172413793,69.65517241379311]},{"type":"Long","lane":6,"time":68.9655172413793},{"type":"Long","lane":6,"time":69.65517241379311},{"type":"Single","lane":5,"time":70.34482758620689},{"type":"Single","lane":2,"time":71.03448275862068},{"type":"Bar","lane":[6,6],"time":[71.72413793103449,72.41379310344827]},{"type":"Long","lane":6,"time":71.72413793103449},{"type":"Long","lane":6,"time":72.41379310344827},{"type":"Single","lane":3,"time":73.10344827586208},{"type":"Single","lane":2,"time":73.79310344827586},{"type":"Single","lane":5,"time":74.48275862068965},{"type":"Single","lane":6,"time":75.17241379310344},{"type":"Skill","lane":3,"time":75.86206896551724},{"type":"Single","lane":5,"time":76.55172413793105},{"type":"Single","lane":6,"time":77.24137931034483},{"type":"Single","lane":2,"time":77.93103448275862},{"type":"Bar","lane":[5,5],"time":[78.62068965517241,79.3103448275862]},{"type":"Long","lane":5,"time":78.62068965517241},{"type":"Long","lane":5,"time":79.3103448275862},{"type":"Bar","lane":[3,3],"time":[80,80.6896551724138]},{"type":"Long","lane":3,"time":80},{"type":"Long","lane":3,"time":80.6896551724138},{"type":"Single","lane":5,"time":81.37931034482759},{"type":"Single","lane":3,"time":82.06896551724138},{"type":"Single","lane":2,"time":82.58620689655172},{"type":"Single","lane":6,"time":82.58620689655172},{"type":"Sim","lane":[2,6],"time":82.58620689655172},{"type":"Single","lane":3,"time":83.44827586206897},{"type":"Single","lane":5,"time":83.44827586206897},{"type":"Sim","lane":[3,5],"time":83.44827586206897},{"type":"Bar","lane":[2,2],"time":[83.79310344827586,86.55172413793103]},{"type":"Long","lane":2,"time":83.79310344827586},{"type":"Bar","lane":[6,6],"time":[83.79310344827586,86.55172413793103]},{"type":"Long","lane":6,"time":83.79310344827586},{"type":"Sim","lane":[2,6],"time":83.79310344827586},{"type":"Long","lane":2,"time":86.55172413793103},{"type":"Long","lane":6,"time":86.55172413793103},{"type":"Sim","lane":[2,6],"time":86.55172413793103},{"type":"Skill","lane":5,"time":86.89655172413794},{"type":"Single","lane":3,"time":88.10344827586208},{"type":"Single","lane":2,"time":89.48275862068965},{"type":"Single","lane":6,"time":90.3448275862069},{"type":"Single","lane":3,"time":91.03448275862068},{"type":"Single","lane":5,"time":91.72413793103448},{"type":"Single","lane":2,"time":92.41379310344827},{"type":"Single","lane":6,"time":93.10344827586206},{"type":"Bar","lane":[2,2],"time":[93.62068965517241,100.6896551724138]},{"type":"Long","lane":2,"time":93.62068965517241},{"type":"Bar","lane":[6,6],"time":[93.62068965517241,100.6896551724138]},{"type":"Long","lane":6,"time":93.62068965517241},{"type":"Sim","lane":[2,6],"time":93.62068965517241},{"type":"Long","lane":2,"time":100.6896551724138},{"type":"Long","lane":6,"time":100.6896551724138},{"type":"Sim","lane":[2,6],"time":100.6896551724138}]