[{"type":"Single","lane":1,"time":2.666666666666667},{"type":"Single","lane":2,"time":4},{"type":"Single","lane":3,"time":5.333333333333334},{"type":"Single","lane":7,"time":6.5},{"type":"Single","lane":1,"time":8},{"type":"Single","lane":3,"time":8.5},{"type":"Single","lane":4,"time":9},{"type":"Bar","lane":[7,7],"time":[9.5,10.666666666666668]},{"type":"Long","lane":7,"time":9.5},{"type":"Long","lane":7,"time":10.666666666666668},{"type":"Single","lane":1,"time":10.666666666666668},{"type":"Sim","lane":[1,7],"time":10.666666666666668},{"type":"Single","lane":3,"time":11.166666666666668},{"type":"Single","lane":4,"time":11.666666666666666},{"type":"Single","lane":7,"time":12.166666666666666},{"type":"Single","lane":6,"time":12.666666666666666},{"type":"Single","lane":5,"time":13},{"type":"Skill","lane":1,"time":13.333333333333332},{"type":"Single","lane":3,"time":13.833333333333334},{"type":"Single","lane":4,"time":14.333333333333334},{"type":"Bar","lane":[7,7],"time":[14.833333333333334,16]},{"type":"Long","lane":7,"time":14.833333333333334},{"type":"Long","lane":7,"time":16},{"type":"Single","lane":3,"time":16},{"type":"Sim","lane":[3,7],"time":16},{"type":"Single","lane":2,"time":16.5},{"type":"Single","lane":6,"time":17},{"type":"Single","lane":5,"time":17.5},{"type":"Single","lane":3,"time":18},{"type":"Single","lane":5,"time":18.333333333333336},{"type":"Single","lane":1,"time":18.666666666666668},{"type":"Single","lane":3,"time":19.166666666666664},{"type":"Single","lane":4,"time":19.666666666666668},{"type":"Bar","lane":[7,7],"time":[20.166666666666668,21]},{"type":"Long","lane":7,"time":20.166666666666668},{"type":"Long","lane":7,"time":21},{"type":"Single","lane":1,"time":21},{"type":"Sim","lane":[1,7],"time":21},{"type":"Single","lane":7,"time":21.166666666666668},{"type":"Single","lane":1,"time":21.333333333333336},{"type":"Single","lane":7,"time":24.5},{"type":"Single","lane":2,"time":24.666666666666664},{"type":"Single","lane":6,"time":25},{"type":"Single","lane":3,"time":25.166666666666668},{"type":"Single","lane":7,"time":25.5},{"type":"Bar","lane":[1,1],"time":[25.833333333333336,26.666666666666664]},{"type":"Long","lane":1,"time":25.833333333333336},{"type":"Long","lane":1,"time":26.666666666666664},{"type":"Skill","lane":1,"time":27.166666666666668},{"type":"Single","lane":6,"time":27.333333333333332},{"type":"Single","lane":2,"time":27.666666666666668},{"type":"Single","lane":5,"time":27.833333333333336},{"type":"Single","lane":1,"time":28.166666666666668},{"type":"Bar","lane":[7,7],"time":[28.5,29.333333333333332]},{"type":"Long","lane":7,"time":28.5},{"type":"Long","lane":7,"time":29.333333333333332},{"type":"Single","lane":6,"time":29.833333333333336},{"type":"Single","lane":2,"time":30},{"type":"Single","lane":5,"time":30.333333333333332},{"type":"Single","lane":3,"time":30.5},{"type":"Single","lane":7,"time":30.83333333333333},{"type":"Single","lane":1,"time":31.166666666666668},{"type":"Single","lane":5,"time":31.666666666666668},{"type":"Single","lane":2,"time":31.833333333333332},{"type":"Single","lane":6,"time":32},{"type":"Single","lane":5,"time":32.5},{"type":"Single","lane":5,"time":33},{"type":"Single","lane":2,"time":34.166666666666664},{"type":"Single","lane":5,"time":34.33333333333333},{"type":"Single","lane":2,"time":34.5},{"type":"Single","lane":7,"time":34.666666666666664},{"type":"Single","lane":6,"time":35},{"type":"Single","lane":5,"time":35.333333333333336},{"type":"Single","lane":4,"time":35.666666666666664},{"type":"Single","lane":3,"time":36},{"type":"Single","lane":2,"time":36.33333333333333},{"type":"Single","lane":5,"time":36.66666666666667},{"type":"Single","lane":6,"time":37},{"type":"Single","lane":1,"time":37.333333333333336},{"type":"Single","lane":2,"time":37.666666666666664},{"type":"Single","lane":3,"time":38},{"type":"Single","lane":4,"time":38.33333333333333},{"type":"Single","lane":5,"time":38.66666666666667},{"type":"Single","lane":6,"time":39},{"type":"Single","lane":3,"time":39.333333333333336},{"type":"Single","lane":2,"time":39.666666666666664},{"type":"Single","lane":7,"time":39.83333333333333},{"type":"Skill","lane":1,"time":40},{"type":"Single","lane":2,"time":40.333333333333336},{"type":"Single","lane":3,"time":40.66666666666667},{"type":"Single","lane":4,"time":41},{"type":"Single","lane":7,"time":41.333333333333336},{"type":"Single","lane":6,"time":41.666666666666664},{"type":"Single","lane":5,"time":42},{"type":"Single","lane":4,"time":42.333333333333336},{"type":"Single","lane":2,"time":42.66666666666667},{"type":"Single","lane":6,"time":43},{"type":"Single","lane":2,"time":43.333333333333336},{"type":"Single","lane":7,"time":43.666666666666664},{"type":"Single","lane":7,"time":44},{"type":"Single","lane":1,"time":44.333333333333336},{"type":"Single","lane":7,"time":44.333333333333336},{"type":"Sim","lane":[1,7],"time":44.333333333333336},{"type":"Single","lane":5,"time":44.66666666666667},{"type":"Single","lane":3,"time":44.833333333333336},{"type":"Single","lane":5,"time":45},{"type":"Bar","lane":[6,6],"time":[45.33333333333333,46]},{"type":"Long","lane":6,"time":45.33333333333333},{"type":"Long","lane":6,"time":46},{"type":"Single","lane":3,"time":46.666666666666664},{"type":"Single","lane":3,"time":47},{"type":"Single","lane":7,"time":47.33333333333333},{"type":"Bar","lane":[2,2],"time":[48,48.666666666666664]},{"type":"Long","lane":2,"time":48},{"type":"Long","lane":2,"time":48.666666666666664},{"type":"Bar","lane":[6,6],"time":[49.33333333333333,50]},{"type":"Long","lane":6,"time":49.33333333333333},{"type":"Long","lane":6,"time":50},{"type":"Bar","lane":[2,2],"time":[50.666666666666664,51.33333333333333]},{"type":"Long","lane":2,"time":50.666666666666664},{"type":"Long","lane":2,"time":51.33333333333333},{"type":"Single","lane":3,"time":51.66666666666667},{"type":"Bar","lane":[7,7],"time":[52,52.666666666666664]},{"type":"Long","lane":7,"time":52},{"type":"Long","lane":7,"time":52.666666666666664},{"type":"Single","lane":6,"time":53},{"type":"Bar","lane":[1,1],"time":[53.33333333333333,54]},{"type":"Long","lane":1,"time":53.33333333333333},{"type":"Long","lane":1,"time":54},{"type":"Single","lane":7,"time":54},{"type":"Sim","lane":[1,7],"time":54},{"type":"Bar","lane":[5,5],"time":[54.666666666666664,55.333333333333336]},{"type":"Long","lane":5,"time":54.666666666666664},{"type":"Long","lane":5,"time":55.333333333333336},{"type":"Single","lane":3,"time":55.333333333333336},{"type":"Sim","lane":[3,5],"time":55.333333333333336},{"type":"Bar","lane":[2,2],"time":[56,56.666666666666664]},{"type":"Long","lane":2,"time":56},{"type":"Long","lane":2,"time":56.666666666666664},{"type":"Single","lane":6,"time":57.333333333333336},{"type":"Single","lane":6,"time":57.66666666666667},{"type":"Single","lane":1,"time":58},{"type":"Bar","lane":[2,2],"time":[58.666666666666664,59.333333333333336]},{"type":"Long","lane":2,"time":58.666666666666664},{"type":"Long","lane":2,"time":59.333333333333336},{"type":"Single","lane":3,"time":59.66666666666667},{"type":"Bar","lane":[5,5],"time":[60,60.666666666666664]},{"type":"Long","lane":5,"time":60},{"type":"Long","lane":5,"time":60.666666666666664},{"type":"Single","lane":2,"time":61},{"type":"Single","lane":5,"time":61.33333333333333},{"type":"Single","lane":3,"time":61.66666666666666},{"type":"Single","lane":7,"time":61.66666666666666},{"type":"Sim","lane":[3,7],"time":61.66666666666666},{"type":"Single","lane":1,"time":62.00000000000001},{"type":"Single","lane":2,"time":62.333333333333336},{"type":"Single","lane":6,"time":62.333333333333336},{"type":"Sim","lane":[2,6],"time":62.333333333333336},{"type":"Single","lane":3,"time":62.66666666666667},{"type":"Single","lane":5,"time":63},{"type":"Single","lane":1,"time":63},{"type":"Sim","lane":[1,5],"time":63},{"type":"Single","lane":7,"time":63.333333333333336},{"type":"Single","lane":2,"time":63.666666666666664},{"type":"Single","lane":6,"time":63.666666666666664},{"type":"Sim","lane":[2,6],"time":63.666666666666664},{"type":"Single","lane":1,"time":64},{"type":"Single","lane":3,"time":64.33333333333333},{"type":"Single","lane":7,"time":64.33333333333333},{"type":"Sim","lane":[3,7],"time":64.33333333333333},{"type":"Single","lane":5,"time":64.66666666666666},{"type":"Single","lane":2,"time":65},{"type":"Single","lane":6,"time":65},{"type":"Sim","lane":[2,6],"time":65},{"type":"Single","lane":7,"time":65.33333333333333},{"type":"Single","lane":5,"time":65.66666666666667},{"type":"Single","lane":1,"time":65.66666666666667},{"type":"Sim","lane":[1,5],"time":65.66666666666667},{"type":"Single","lane":3,"time":66},{"type":"Single","lane":6,"time":66.33333333333334},{"type":"Single","lane":2,"time":66.5},{"type":"Single","lane":7,"time":67},{"type":"Single","lane":6,"time":67.33333333333333},{"type":"Single","lane":5,"time":67.66666666666667},{"type":"Single","lane":3,"time":68},{"type":"Single","lane":2,"time":68.33333333333333},{"type":"Single","lane":1,"time":68.66666666666666},{"type":"Single","lane":7,"time":68.83333333333333},{"type":"Single","lane":1,"time":69},{"type":"Single","lane":7,"time":69.16666666666666},{"type":"Single","lane":1,"time":69.33333333333333},{"type":"Single","lane":6,"time":72},{"type":"Single","lane":6,"time":72.5},{"type":"Single","lane":6,"time":73},{"type":"Single","lane":6,"time":73.5},{"type":"Skill","lane":2,"time":74.66666666666667},{"type":"Single","lane":2,"time":75.16666666666667},{"type":"Single","lane":2,"time":75.66666666666666},{"type":"Single","lane":2,"time":76.16666666666666},{"type":"Single","lane":7,"time":77.33333333333334},{"type":"Single","lane":5,"time":77.83333333333334},{"type":"Single","lane":3,"time":78.33333333333333},{"type":"Single","lane":1,"time":78.83333333333333},{"type":"Single","lane":1,"time":80},{"type":"Single","lane":3,"time":80.5},{"type":"Single","lane":5,"time":81},{"type":"Single","lane":7,"time":81.5},{"type":"Single","lane":3,"time":82},{"type":"Single","lane":5,"time":82.33333333333333},{"type":"Single","lane":1,"time":82.66666666666667},{"type":"Single","lane":6,"time":83},{"type":"Single","lane":3,"time":83.33333333333333},{"type":"Single","lane":6,"time":83.66666666666666},{"type":"Single","lane":1,"time":84},{"type":"Single","lane":6,"time":84.33333333333333},{"type":"Single","lane":2,"time":84.66666666666667},{"type":"Single","lane":5,"time":84.83333333333334},{"type":"Single","lane":2,"time":85},{"type":"Single","lane":1,"time":85.33333333333334},{"type":"Single","lane":6,"time":85.66666666666667},{"type":"Single","lane":3,"time":86},{"type":"Single","lane":6,"time":86.33333333333333},{"type":"Single","lane":1,"time":86.66666666666667},{"type":"Single","lane":6,"time":87},{"type":"Single","lane":2,"time":87.33333333333333},{"type":"Single","lane":6,"time":87.66666666666666},{"type":"Skill","lane":7,"time":88},{"type":"Bar","lane":[7,7],"time":[88,88.5]},{"type":"Long","lane":7,"time":88.5},{"type":"Bar","lane":[2,2],"time":[88.5,89]},{"type":"Long","lane":2,"time":88.5},{"type":"Sim","lane":[2,7],"time":88.5},{"type":"Long","lane":2,"time":89},{"type":"Single","lane":5,"time":89},{"type":"Sim","lane":[2,5],"time":89},{"type":"Bar","lane":[1,1],"time":[89.33333333333334,89.83333333333333]},{"type":"Long","lane":1,"time":89.33333333333334},{"type":"Long","lane":1,"time":89.83333333333333},{"type":"Bar","lane":[6,6],"time":[89.83333333333333,90.33333333333333]},{"type":"Long","lane":6,"time":89.83333333333333},{"type":"Sim","lane":[1,6],"time":89.83333333333333},{"type":"Long","lane":6,"time":90.33333333333333},{"type":"Single","lane":3,"time":90.33333333333333},{"type":"Sim","lane":[3,6],"time":90.33333333333333},{"type":"Single","lane":5,"time":90.66666666666666},{"type":"Single","lane":2,"time":91},{"type":"Single","lane":4,"time":91.16666666666666},{"type":"Single","lane":5,"time":91.5},{"type":"Bar","lane":[5,5],"time":[91.83333333333333,92.33333333333334]},{"type":"Long","lane":5,"time":91.83333333333333},{"type":"Long","lane":5,"time":92.33333333333334},{"type":"Bar","lane":[1,1],"time":[92.33333333333334,92.66666666666667]},{"type":"Long","lane":1,"time":92.33333333333334},{"type":"Sim","lane":[1,5],"time":92.33333333333334},{"type":"Long","lane":1,"time":92.66666666666667},{"type":"Bar","lane":[7,7],"time":[92.66666666666667,93]},{"type":"Long","lane":7,"time":92.66666666666667},{"type":"Sim","lane":[1,7],"time":92.66666666666667},{"type":"Long","lane":7,"time":93},{"type":"Bar","lane":[3,3],"time":[93,93.16666666666667]},{"type":"Long","lane":3,"time":93},{"type":"Sim","lane":[3,7],"time":93},{"type":"Long","lane":3,"time":93.16666666666667},{"type":"Bar","lane":[5,5],"time":[93.16666666666667,94]},{"type":"Long","lane":5,"time":93.16666666666667},{"type":"Sim","lane":[3,5],"time":93.16666666666667},{"type":"Long","lane":5,"time":94},{"type":"Single","lane":5,"time":94.33333333333333},{"type":"Single","lane":3,"time":94.5},{"type":"Single","lane":5,"time":94.66666666666666},{"type":"Single","lane":2,"time":95},{"type":"Single","lane":6,"time":95.16666666666666},{"type":"Single","lane":7,"time":95.66666666666667},{"type":"Single","lane":1,"time":95.83333333333334},{"type":"Single","lane":6,"time":98.66666666666666},{"type":"Single","lane":1,"time":98.66666666666666},{"type":"Sim","lane":[1,6],"time":98.66666666666666},{"type":"Single","lane":3,"time":99},{"type":"Single","lane":3,"time":99.33333333333333},{"type":"Single","lane":3,"time":99.66666666666667},{"type":"Single","lane":3,"time":100},{"type":"Single","lane":3,"time":100.33333333333334},{"type":"Single","lane":3,"time":100.66666666666667},{"type":"Single","lane":3,"time":101},{"type":"Skill","lane":7,"time":101.33333333333333},{"type":"Single","lane":2,"time":101.33333333333333},{"type":"Sim","lane":[2,7],"time":101.33333333333333},{"type":"Single","lane":5,"time":101.66666666666667},{"type":"Single","lane":5,"time":102},{"type":"Single","lane":5,"time":102.33333333333333},{"type":"Single","lane":5,"time":102.66666666666666},{"type":"Single","lane":5,"time":103},{"type":"Single","lane":5,"time":103.33333333333334},{"type":"Single","lane":5,"time":103.66666666666667},{"type":"Single","lane":3,"time":104},{"type":"Single","lane":6,"time":104},{"type":"Sim","lane":[3,6],"time":104},{"type":"Single","lane":1,"time":104.33333333333334},{"type":"Single","lane":1,"time":104.66666666666667},{"type":"Single","lane":1,"time":105},{"type":"Single","lane":1,"time":105.33333333333333},{"type":"Single","lane":1,"time":105.66666666666666},{"type":"Single","lane":1,"time":106},{"type":"Single","lane":1,"time":106.33333333333333},{"type":"Single","lane":2,"time":106.66666666666666},{"type":"Single","lane":5,"time":106.66666666666666},{"type":"Sim","lane":[2,5],"time":106.66666666666666},{"type":"Single","lane":7,"time":107},{"type":"Single","lane":7,"time":107.33333333333334},{"type":"Single","lane":7,"time":107.66666666666667},{"type":"Single","lane":2,"time":108},{"type":"Single","lane":6,"time":108},{"type":"Sim","lane":[2,6],"time":108},{"type":"Single","lane":4,"time":108.33333333333333},{"type":"Single","lane":7,"time":108.66666666666667},{"type":"Single","lane":1,"time":108.83333333333333},{"type":"Single","lane":5,"time":109},{"type":"Single","lane":3,"time":109.16666666666667},{"type":"Single","lane":6,"time":109.33333333333333},{"type":"Single","lane":2,"time":109.66666666666666},{"type":"Single","lane":7,"time":109.66666666666666},{"type":"Sim","lane":[2,7],"time":109.66666666666666},{"type":"Single","lane":3,"time":110},{"type":"Single","lane":2,"time":110.33333333333333},{"type":"Single","lane":6,"time":110.33333333333333},{"type":"Sim","lane":[2,6],"time":110.33333333333333},{"type":"Single","lane":5,"time":110.66666666666667},{"type":"Single","lane":6,"time":111},{"type":"Single","lane":1,"time":111},{"type":"Sim","lane":[1,6],"time":111},{"type":"Single","lane":3,"time":111.33333333333334},{"type":"Single","lane":6,"time":111.66666666666667},{"type":"Single","lane":2,"time":111.83333333333334},{"type":"Bar","lane":[6,6],"time":[112,114.66666666666667]},{"type":"Long","lane":6,"time":112},{"type":"Long","lane":6,"time":114.66666666666667},{"type":"Single","lane":1,"time":114.66666666666667},{"type":"Sim","lane":[1,6],"time":114.66666666666667},{"type":"Single","lane":2,"time":116},{"type":"Single","lane":3,"time":117.33333333333333},{"type":"Single","lane":7,"time":118.5}]