[{"type":"Single","lane":5,"time":3.380281690140845},{"type":"Single","lane":3,"time":4.014084507042253},{"type":"Single","lane":2,"time":4.859154929577465},{"type":"Single","lane":7,"time":4.859154929577465},{"type":"Sim","lane":[2,7],"time":4.859154929577465},{"type":"Single","lane":5,"time":6.76056338028169},{"type":"Single","lane":3,"time":7.394366197183099},{"type":"Bar","lane":[2,2],"time":[8.450704225352114,8.873239436619718]},{"type":"Long","lane":2,"time":8.450704225352114},{"type":"Long","lane":2,"time":8.873239436619718},{"type":"Bar","lane":[6,6],"time":[9.08450704225352,9.507042253521128]},{"type":"Long","lane":6,"time":9.08450704225352},{"type":"Long","lane":6,"time":9.507042253521128},{"type":"Skill","lane":1,"time":10.140845070422536},{"type":"Single","lane":1,"time":10.56338028169014},{"type":"Single","lane":5,"time":11.19718309859155},{"type":"Single","lane":2,"time":11.830985915492956},{"type":"Single","lane":2,"time":12.253521126760564},{"type":"Single","lane":3,"time":12.887323943661972},{"type":"Single","lane":7,"time":12.887323943661972},{"type":"Sim","lane":[3,7],"time":12.887323943661972},{"type":"Single","lane":6,"time":13.52112676056338},{"type":"Single","lane":6,"time":13.943661971830986},{"type":"Single","lane":2,"time":14.577464788732396},{"type":"Single","lane":7,"time":15.211267605633802},{"type":"Single","lane":7,"time":15.633802816901408},{"type":"Single","lane":5,"time":16.26760563380282},{"type":"Single","lane":1,"time":16.26760563380282},{"type":"Sim","lane":[1,5],"time":16.26760563380282},{"type":"Single","lane":2,"time":16.901408450704228},{"type":"Single","lane":2,"time":17.323943661971832},{"type":"Single","lane":6,"time":17.95774647887324},{"type":"Single","lane":3,"time":18.591549295774648},{"type":"Single","lane":3,"time":19.014084507042256},{"type":"Single","lane":2,"time":19.647887323943664},{"type":"Single","lane":7,"time":19.647887323943664},{"type":"Sim","lane":[2,7],"time":19.647887323943664},{"type":"Single","lane":6,"time":20.281690140845072},{"type":"Single","lane":6,"time":20.704225352112676},{"type":"Single","lane":3,"time":21.338028169014088},{"type":"Single","lane":5,"time":21.971830985915492},{"type":"Single","lane":5,"time":22.3943661971831},{"type":"Single","lane":6,"time":23.028169014084508},{"type":"Single","lane":1,"time":23.028169014084508},{"type":"Sim","lane":[1,6],"time":23.028169014084508},{"type":"Skill","lane":3,"time":23.661971830985912},{"type":"Single","lane":6,"time":24.507042253521128},{"type":"Single","lane":1,"time":25.352112676056336},{"type":"Single","lane":5,"time":25.774647887323944},{"type":"Single","lane":3,"time":26.197183098591548},{"type":"Single","lane":7,"time":26.619718309859156},{"type":"Bar","lane":[1,1],"time":[27.04225352112676,27.887323943661972]},{"type":"Long","lane":1,"time":27.04225352112676},{"type":"Long","lane":1,"time":27.887323943661972},{"type":"Single","lane":6,"time":27.887323943661972},{"type":"Sim","lane":[1,6],"time":27.887323943661972},{"type":"Single","lane":5,"time":28.73239436619718},{"type":"Single","lane":3,"time":29.15492957746479},{"type":"Single","lane":6,"time":29.577464788732396},{"type":"Single","lane":2,"time":30},{"type":"Single","lane":5,"time":30.422535211267604},{"type":"Single","lane":1,"time":31.267605633802816},{"type":"Single","lane":5,"time":32.112676056338024},{"type":"Single","lane":2,"time":32.53521126760564},{"type":"Single","lane":6,"time":32.95774647887324},{"type":"Single","lane":3,"time":33.38028169014085},{"type":"Bar","lane":[7,7],"time":[33.802816901408455,34.436619718309856]},{"type":"Long","lane":7,"time":33.802816901408455},{"type":"Long","lane":7,"time":34.436619718309856},{"type":"Bar","lane":[2,2],"time":[34.436619718309856,35.070422535211264]},{"type":"Long","lane":2,"time":34.436619718309856},{"type":"Sim","lane":[2,7],"time":34.436619718309856},{"type":"Long","lane":2,"time":35.070422535211264},{"type":"Single","lane":6,"time":35.070422535211264},{"type":"Sim","lane":[2,6],"time":35.070422535211264},{"type":"Single","lane":5,"time":35.91549295774648},{"type":"Single","lane":3,"time":36.33802816901408},{"type":"Single","lane":1,"time":36.76056338028169},{"type":"Single","lane":7,"time":36.76056338028169},{"type":"Sim","lane":[1,7],"time":36.76056338028169},{"type":"Single","lane":6,"time":37.183098591549296},{"type":"Single","lane":3,"time":37.605633802816904},{"type":"Single","lane":5,"time":38.02816901408451},{"type":"Single","lane":2,"time":38.45070422535211},{"type":"Single","lane":7,"time":38.87323943661972},{"type":"Single","lane":3,"time":39.29577464788733},{"type":"Single","lane":5,"time":39.71830985915493},{"type":"Single","lane":1,"time":40.140845070422536},{"type":"Bar","lane":[6,6],"time":[40.563380281690144,41.40845070422535]},{"type":"Long","lane":6,"time":40.563380281690144},{"type":"Long","lane":6,"time":41.40845070422535},{"type":"Single","lane":2,"time":41.40845070422535},{"type":"Sim","lane":[2,6],"time":41.40845070422535},{"type":"Single","lane":3,"time":42.25352112676056},{"type":"Single","lane":5,"time":42.676056338028175},{"type":"Single","lane":2,"time":43.098591549295776},{"type":"Skill","lane":6,"time":43.521126760563384},{"type":"Single","lane":1,"time":43.943661971830984},{"type":"Single","lane":5,"time":44.36619718309859},{"type":"Single","lane":2,"time":44.7887323943662},{"type":"Single","lane":6,"time":45.2112676056338},{"type":"Single","lane":3,"time":45.63380281690141},{"type":"Single","lane":5,"time":46.056338028169016},{"type":"Single","lane":2,"time":46.478873239436616},{"type":"Single","lane":7,"time":46.901408450704224},{"type":"Bar","lane":[1,1],"time":[47.323943661971825,47.95774647887324]},{"type":"Long","lane":1,"time":47.323943661971825},{"type":"Long","lane":1,"time":47.95774647887324},{"type":"Bar","lane":[6,6],"time":[47.95774647887324,48.59154929577465]},{"type":"Long","lane":6,"time":47.95774647887324},{"type":"Sim","lane":[1,6],"time":47.95774647887324},{"type":"Long","lane":6,"time":48.59154929577465},{"type":"Single","lane":2,"time":48.59154929577465},{"type":"Sim","lane":[2,6],"time":48.59154929577465},{"type":"Single","lane":3,"time":49.436619718309856},{"type":"Single","lane":5,"time":49.859154929577464},{"type":"Single","lane":1,"time":50.28169014084507},{"type":"Single","lane":7,"time":50.28169014084507},{"type":"Sim","lane":[1,7],"time":50.28169014084507},{"type":"Bar","lane":[2,2],"time":[50.70422535211267,51.54929577464789]},{"type":"Long","lane":2,"time":50.70422535211267},{"type":"Long","lane":2,"time":51.54929577464789},{"type":"Bar","lane":[6,6],"time":[52.394366197183096,53.23943661971831]},{"type":"Long","lane":6,"time":52.394366197183096},{"type":"Long","lane":6,"time":53.23943661971831},{"type":"Bar","lane":[2,2],"time":[54.08450704225352,55.774647887323944]},{"type":"Long","lane":2,"time":54.08450704225352},{"type":"Long","lane":2,"time":55.774647887323944},{"type":"Single","lane":3,"time":56.61971830985915},{"type":"Single","lane":5,"time":57.04225352112676},{"type":"Single","lane":3,"time":57.46478873239436},{"type":"Single","lane":6,"time":58.30985915492958},{"type":"Single","lane":2,"time":58.521126760563384},{"type":"Single","lane":6,"time":58.732394366197184},{"type":"Single","lane":5,"time":59.15492957746479},{"type":"Single","lane":2,"time":60},{"type":"Single","lane":6,"time":60.21126760563381},{"type":"Single","lane":2,"time":60.42253521126761},{"type":"Bar","lane":[3,3],"time":[60.84507042253521,62.32394366197183]},{"type":"Long","lane":3,"time":60.84507042253521},{"type":"Bar","lane":[5,5],"time":[60.84507042253521,62.32394366197183]},{"type":"Long","lane":5,"time":60.84507042253521},{"type":"Sim","lane":[3,5],"time":60.84507042253521},{"type":"Long","lane":3,"time":62.32394366197183},{"type":"Long","lane":5,"time":62.32394366197183},{"type":"Sim","lane":[3,5],"time":62.32394366197183},{"type":"Single","lane":1,"time":62.74647887323944},{"type":"Single","lane":7,"time":62.74647887323944},{"type":"Sim","lane":[1,7],"time":62.74647887323944},{"type":"Single","lane":1,"time":62.95774647887323},{"type":"Single","lane":7,"time":62.95774647887323},{"type":"Sim","lane":[1,7],"time":62.95774647887323},{"type":"Bar","lane":[2,2],"time":[64.22535211267605,66.3380281690141]},{"type":"Long","lane":2,"time":64.22535211267605},{"type":"Bar","lane":[6,6],"time":[64.22535211267605,66.3380281690141]},{"type":"Long","lane":6,"time":64.22535211267605},{"type":"Sim","lane":[2,6],"time":64.22535211267605},{"type":"Long","lane":2,"time":66.3380281690141},{"type":"Long","lane":6,"time":66.3380281690141},{"type":"Sim","lane":[2,6],"time":66.3380281690141},{"type":"Single","lane":3,"time":66.7605633802817},{"type":"Single","lane":5,"time":67.1830985915493},{"type":"Single","lane":3,"time":67.60563380281691},{"type":"Single","lane":6,"time":68.2394366197183},{"type":"Single","lane":1,"time":68.6619718309859},{"type":"Single","lane":5,"time":69.08450704225352},{"type":"Single","lane":3,"time":69.50704225352112},{"type":"Bar","lane":[6,6],"time":[69.92957746478872,70.56338028169014]},{"type":"Long","lane":6,"time":69.92957746478872},{"type":"Long","lane":6,"time":70.56338028169014},{"type":"Single","lane":2,"time":70.56338028169014},{"type":"Sim","lane":[2,6],"time":70.56338028169014},{"type":"Skill","lane":1,"time":70.98591549295774},{"type":"Single","lane":7,"time":70.98591549295774},{"type":"Sim","lane":[1,7],"time":70.98591549295774},{"type":"Single","lane":5,"time":71.61971830985917},{"type":"Single","lane":2,"time":72.04225352112677},{"type":"Single","lane":6,"time":72.46478873239437},{"type":"Single","lane":3,"time":72.88732394366197},{"type":"Single","lane":7,"time":73.30985915492958},{"type":"Single","lane":2,"time":73.73239436619718},{"type":"Single","lane":6,"time":74.15492957746478},{"type":"Single","lane":3,"time":74.36619718309859},{"type":"Single","lane":5,"time":75},{"type":"Single","lane":2,"time":75.21126760563381},{"type":"Single","lane":6,"time":75.84507042253522},{"type":"Single","lane":3,"time":76.05633802816902},{"type":"Single","lane":2,"time":76.69014084507042},{"type":"Single","lane":5,"time":77.11267605633803},{"type":"Single","lane":3,"time":77.32394366197184},{"type":"Bar","lane":[2,2],"time":[77.74647887323944,79.85915492957747]},{"type":"Long","lane":2,"time":77.74647887323944},{"type":"Bar","lane":[6,6],"time":[77.74647887323944,79.85915492957747]},{"type":"Long","lane":6,"time":77.74647887323944},{"type":"Sim","lane":[2,6],"time":77.74647887323944},{"type":"Long","lane":2,"time":79.85915492957747},{"type":"Long","lane":6,"time":79.85915492957747},{"type":"Sim","lane":[2,6],"time":79.85915492957747},{"type":"Single","lane":5,"time":80.28169014084507},{"type":"Single","lane":3,"time":80.70422535211267},{"type":"Skill","lane":6,"time":81.12676056338029},{"type":"Single","lane":1,"time":81.7605633802817},{"type":"Single","lane":5,"time":82.1830985915493},{"type":"Single","lane":3,"time":82.60563380281691},{"type":"Single","lane":6,"time":83.02816901408451},{"type":"Bar","lane":[2,2],"time":[83.45070422535211,84.08450704225352]},{"type":"Long","lane":2,"time":83.45070422535211},{"type":"Long","lane":2,"time":84.08450704225352},{"type":"Single","lane":5,"time":84.08450704225352},{"type":"Sim","lane":[2,5],"time":84.08450704225352},{"type":"Single","lane":1,"time":84.50704225352112},{"type":"Single","lane":7,"time":84.50704225352112},{"type":"Sim","lane":[1,7],"time":84.50704225352112},{"type":"Single","lane":3,"time":85.14084507042253},{"type":"Single","lane":5,"time":85.56338028169014},{"type":"Single","lane":1,"time":85.98591549295774},{"type":"Single","lane":7,"time":86.40845070422534},{"type":"Single","lane":2,"time":86.83098591549296},{"type":"Single","lane":6,"time":87.25352112676056},{"type":"Single","lane":3,"time":87.67605633802816},{"type":"Single","lane":5,"time":87.88732394366197},{"type":"Single","lane":2,"time":88.52112676056338},{"type":"Single","lane":6,"time":88.73239436619718},{"type":"Single","lane":3,"time":89.36619718309859},{"type":"Single","lane":5,"time":89.5774647887324},{"type":"Bar","lane":[2,2],"time":[90.21126760563381,90.84507042253522]},{"type":"Long","lane":2,"time":90.21126760563381},{"type":"Bar","lane":[6,6],"time":[90.21126760563381,90.84507042253522]},{"type":"Long","lane":6,"time":90.21126760563381},{"type":"Sim","lane":[2,6],"time":90.21126760563381},{"type":"Long","lane":2,"time":90.84507042253522},{"type":"Long","lane":6,"time":90.84507042253522},{"type":"Sim","lane":[2,6],"time":90.84507042253522},{"type":"Skill","lane":5,"time":91.26760563380282},{"type":"Single","lane":2,"time":91.69014084507042},{"type":"Single","lane":6,"time":92.11267605633803},{"type":"Single","lane":3,"time":92.53521126760563},{"type":"Single","lane":5,"time":92.95774647887323},{"type":"Single","lane":2,"time":93.38028169014083},{"type":"Bar","lane":[7,7],"time":[93.80281690140845,94.22535211267605]},{"type":"Long","lane":7,"time":93.80281690140845},{"type":"Long","lane":7,"time":94.22535211267605},{"type":"Single","lane":1,"time":94.64788732394365},{"type":"Single","lane":5,"time":95.07042253521128},{"type":"Single","lane":2,"time":95.49295774647888},{"type":"Single","lane":6,"time":95.91549295774648},{"type":"Single","lane":1,"time":96.3380281690141},{"type":"Bar","lane":[5,5],"time":[96.7605633802817,97.60563380281691]},{"type":"Long","lane":5,"time":96.7605633802817},{"type":"Long","lane":5,"time":97.60563380281691},{"type":"Single","lane":2,"time":98.02816901408451},{"type":"Single","lane":6,"time":98.45070422535211},{"type":"Single","lane":3,"time":98.87323943661971},{"type":"Single","lane":5,"time":99.29577464788733},{"type":"Single","lane":2,"time":99.71830985915493},{"type":"Single","lane":6,"time":100.14084507042253},{"type":"Bar","lane":[1,1],"time":[100.56338028169014,100.98591549295774]},{"type":"Long","lane":1,"time":100.56338028169014},{"type":"Long","lane":1,"time":100.98591549295774},{"type":"Single","lane":7,"time":101.40845070422534},{"type":"Single","lane":3,"time":101.83098591549296},{"type":"Single","lane":5,"time":102.25352112676056},{"type":"Single","lane":1,"time":102.67605633802816},{"type":"Single","lane":2,"time":103.09859154929578},{"type":"Single","lane":6,"time":103.09859154929578},{"type":"Sim","lane":[2,6],"time":103.09859154929578},{"type":"Single","lane":5,"time":103.73239436619718},{"type":"Single","lane":1,"time":103.73239436619718},{"type":"Sim","lane":[1,5],"time":103.73239436619718},{"type":"Single","lane":2,"time":104.36619718309859},{"type":"Single","lane":6,"time":104.36619718309859},{"type":"Sim","lane":[2,6],"time":104.36619718309859},{"type":"Bar","lane":[1,1],"time":[104.78873239436619,106.47887323943662]},{"type":"Long","lane":1,"time":104.78873239436619},{"type":"Bar","lane":[7,7],"time":[104.78873239436619,106.47887323943662]},{"type":"Long","lane":7,"time":104.78873239436619},{"type":"Sim","lane":[1,7],"time":104.78873239436619},{"type":"Long","lane":1,"time":106.47887323943662},{"type":"Long","lane":7,"time":106.47887323943662},{"type":"Sim","lane":[1,7],"time":106.47887323943662}]