[{"type":"Single","lane":6,"time":5},{"type":"Bar","lane":[2,2],"time":[6.25,6.875]},{"type":"Long","lane":2,"time":6.25},{"type":"Long","lane":2,"time":6.875},{"type":"Single","lane":5,"time":7.5},{"type":"Bar","lane":[7,7],"time":[8.75,9.375]},{"type":"Long","lane":7,"time":8.75},{"type":"Long","lane":7,"time":9.375},{"type":"Skill","lane":5,"time":10},{"type":"Single","lane":2,"time":10},{"type":"Sim","lane":[2,5],"time":10},{"type":"Single","lane":3,"time":11.25},{"type":"Single","lane":6,"time":11.25},{"type":"Sim","lane":[3,6],"time":11.25},{"type":"Single","lane":5,"time":12.5},{"type":"Single","lane":1,"time":12.5},{"type":"Sim","lane":[1,5],"time":12.5},{"type":"Single","lane":3,"time":13.75},{"type":"Single","lane":6,"time":14.375},{"type":"Bar","lane":[1,1],"time":[15,16.25]},{"type":"Long","lane":1,"time":15},{"type":"Bar","lane":[7,7],"time":[15,16.25]},{"type":"Long","lane":7,"time":15},{"type":"Sim","lane":[1,7],"time":15},{"type":"Long","lane":1,"time":16.25},{"type":"Long","lane":7,"time":16.25},{"type":"Sim","lane":[1,7],"time":16.25},{"type":"Single","lane":2,"time":16.875},{"type":"Single","lane":6,"time":16.875},{"type":"Sim","lane":[2,6],"time":16.875},{"type":"Bar","lane":[2,2],"time":[17.34375,17.8125]},{"type":"Long","lane":2,"time":17.34375},{"type":"Long","lane":2,"time":17.8125},{"type":"Single","lane":2,"time":18.125},{"type":"Bar","lane":[6,6],"time":[18.59375,19.0625]},{"type":"Long","lane":6,"time":18.59375},{"type":"Long","lane":6,"time":19.0625},{"type":"Single","lane":6,"time":19.375},{"type":"Bar","lane":[1,1],"time":[19.84375,20.3125]},{"type":"Long","lane":1,"time":19.84375},{"type":"Long","lane":1,"time":20.3125},{"type":"Single","lane":1,"time":20.625},{"type":"Bar","lane":[5,5],"time":[21.09375,21.5625]},{"type":"Long","lane":5,"time":21.09375},{"type":"Long","lane":5,"time":21.5625},{"type":"Single","lane":2,"time":21.875},{"type":"Single","lane":5,"time":21.875},{"type":"Sim","lane":[2,5],"time":21.875},{"type":"Bar","lane":[1,1],"time":[22.5,22.96875]},{"type":"Long","lane":1,"time":22.5},{"type":"Bar","lane":[7,7],"time":[22.5,22.96875]},{"type":"Long","lane":7,"time":22.5},{"type":"Sim","lane":[1,7],"time":22.5},{"type":"Long","lane":1,"time":22.96875},{"type":"Long","lane":7,"time":22.96875},{"type":"Sim","lane":[1,7],"time":22.96875},{"type":"Bar","lane":[3,3],"time":[23.4375,24.375]},{"type":"Long","lane":3,"time":23.4375},{"type":"Bar","lane":[5,5],"time":[23.4375,24.375]},{"type":"Long","lane":5,"time":23.4375},{"type":"Sim","lane":[3,5],"time":23.4375},{"type":"Long","lane":3,"time":24.375},{"type":"Long","lane":5,"time":24.375},{"type":"Sim","lane":[3,5],"time":24.375},{"type":"Bar","lane":[2,2],"time":[24.84375,26.09375]},{"type":"Long","lane":2,"time":24.84375},{"type":"Bar","lane":[6,6],"time":[24.84375,26.09375]},{"type":"Long","lane":6,"time":24.84375},{"type":"Sim","lane":[2,6],"time":24.84375},{"type":"Long","lane":2,"time":26.09375},{"type":"Long","lane":6,"time":26.09375},{"type":"Sim","lane":[2,6],"time":26.09375},{"type":"SingleOff","lane":2,"time":27.03125},{"type":"SingleOff","lane":6,"time":27.03125},{"type":"Sim","lane":[2,6],"time":27.03125},{"type":"Single","lane":5,"time":27.5},{"type":"Single","lane":3,"time":28.125},{"type":"Single","lane":5,"time":28.75},{"type":"Single","lane":3,"time":29.375},{"type":"Skill","lane":7,"time":30},{"type":"Bar","lane":[7,7],"time":[30,31.250000000000004]},{"type":"Long","lane":7,"time":31.250000000000004},{"type":"Bar","lane":[1,1],"time":[32.5,33.75]},{"type":"Long","lane":1,"time":32.5},{"type":"Long","lane":1,"time":33.75},{"type":"Single","lane":6,"time":35},{"type":"Single","lane":5,"time":36.25},{"type":"Single","lane":3,"time":36.875},{"type":"Bar","lane":[2,2],"time":[37.5,38.4375]},{"type":"Long","lane":2,"time":37.5},{"type":"Bar","lane":[6,6],"time":[37.5,38.4375]},{"type":"Long","lane":6,"time":37.5},{"type":"Sim","lane":[2,6],"time":37.5},{"type":"Long","lane":2,"time":38.4375},{"type":"Long","lane":6,"time":38.4375},{"type":"Sim","lane":[2,6],"time":38.4375},{"type":"Bar","lane":[1,1],"time":[40,41.25]},{"type":"Long","lane":1,"time":40},{"type":"Long","lane":1,"time":41.25},{"type":"Single","lane":6,"time":41.875},{"type":"Bar","lane":[7,7],"time":[42.5,43.75]},{"type":"Long","lane":7,"time":42.5},{"type":"Long","lane":7,"time":43.75},{"type":"Single","lane":2,"time":44.375},{"type":"Skill","lane":6,"time":45},{"type":"Single","lane":3,"time":46.25},{"type":"Single","lane":6,"time":47.5},{"type":"Single","lane":3,"time":48.125},{"type":"Single","lane":5,"time":48.75},{"type":"Single","lane":2,"time":49.375},{"type":"Single","lane":1,"time":50},{"type":"Single","lane":7,"time":50},{"type":"Sim","lane":[1,7],"time":50},{"type":"Single","lane":3,"time":51.25},{"type":"Single","lane":6,"time":51.25},{"type":"Sim","lane":[3,6],"time":51.25},{"type":"Single","lane":2,"time":51.875},{"type":"Single","lane":5,"time":52.5},{"type":"Single","lane":1,"time":52.5},{"type":"Sim","lane":[1,5],"time":52.5},{"type":"Bar","lane":[2,2],"time":[53.75,54.375]},{"type":"Long","lane":2,"time":53.75},{"type":"Bar","lane":[6,6],"time":[53.75,54.375]},{"type":"Long","lane":6,"time":53.75},{"type":"Sim","lane":[2,6],"time":53.75},{"type":"Long","lane":2,"time":54.375},{"type":"Long","lane":6,"time":54.375},{"type":"Sim","lane":[2,6],"time":54.375},{"type":"Single","lane":3,"time":55},{"type":"Single","lane":7,"time":55},{"type":"Sim","lane":[3,7],"time":55},{"type":"Single","lane":6,"time":56.25},{"type":"Single","lane":1,"time":56.25},{"type":"Sim","lane":[1,6],"time":56.25},{"type":"Single","lane":5,"time":56.875},{"type":"Bar","lane":[2,2],"time":[57.5,58.125]},{"type":"Long","lane":2,"time":57.5},{"type":"Bar","lane":[6,6],"time":[57.5,58.125]},{"type":"Long","lane":6,"time":57.5},{"type":"Sim","lane":[2,6],"time":57.5},{"type":"Long","lane":2,"time":58.125},{"type":"Long","lane":6,"time":58.125},{"type":"Sim","lane":[2,6],"time":58.125},{"type":"Single","lane":3,"time":58.75},{"type":"Single","lane":5,"time":58.75},{"type":"Sim","lane":[3,5],"time":58.75},{"type":"Single","lane":3,"time":59.0625},{"type":"Single","lane":5,"time":59.0625},{"type":"Sim","lane":[3,5],"time":59.0625},{"type":"Single","lane":3,"time":59.375},{"type":"Single","lane":5,"time":59.375},{"type":"Sim","lane":[3,5],"time":59.375},{"type":"Single","lane":1,"time":60},{"type":"Single","lane":6,"time":61.24999999999999},{"type":"Single","lane":2,"time":62.50000000000001},{"type":"Single","lane":7,"time":63.75},{"type":"Bar","lane":[1,1],"time":[65,66.875]},{"type":"Long","lane":1,"time":65},{"type":"Bar","lane":[7,7],"time":[65,66.875]},{"type":"Long","lane":7,"time":65},{"type":"Sim","lane":[1,7],"time":65},{"type":"Long","lane":1,"time":66.875},{"type":"Long","lane":7,"time":66.875},{"type":"Sim","lane":[1,7],"time":66.875},{"type":"Bar","lane":[2,2],"time":[67.5,68.59375]},{"type":"Long","lane":2,"time":67.5},{"type":"Bar","lane":[6,6],"time":[67.5,68.59375]},{"type":"Long","lane":6,"time":67.5},{"type":"Sim","lane":[2,6],"time":67.5},{"type":"Long","lane":2,"time":68.59375},{"type":"Long","lane":6,"time":68.59375},{"type":"Sim","lane":[2,6],"time":68.59375},{"type":"Single","lane":3,"time":69.0625},{"type":"Single","lane":3,"time":69.375},{"type":"Single","lane":3,"time":69.6875},{"type":"Single","lane":6,"time":70},{"type":"Single","lane":2,"time":70.3125},{"type":"Single","lane":6,"time":70.625},{"type":"Single","lane":1,"time":71.25},{"type":"Single","lane":5,"time":71.5625},{"type":"Single","lane":1,"time":71.875},{"type":"Single","lane":7,"time":72.5},{"type":"Single","lane":7,"time":72.8125},{"type":"Single","lane":7,"time":73.125},{"type":"Single","lane":2,"time":73.75},{"type":"Single","lane":6,"time":74.0625},{"type":"Single","lane":2,"time":74.375},{"type":"Bar","lane":[7,7],"time":[75,75.3125]},{"type":"Long","lane":7,"time":75},{"type":"Long","lane":7,"time":75.3125},{"type":"Skill","lane":3,"time":75.625},{"type":"Bar","lane":[2,2],"time":[76.25,76.5625]},{"type":"Long","lane":2,"time":76.25},{"type":"Long","lane":2,"time":76.5625},{"type":"Single","lane":5,"time":76.875},{"type":"Single","lane":2,"time":77.5},{"type":"Single","lane":6,"time":77.5},{"type":"Sim","lane":[2,6],"time":77.5},{"type":"Bar","lane":[2,2],"time":[78.75,79.375]},{"type":"Long","lane":2,"time":78.75},{"type":"Bar","lane":[6,6],"time":[78.75,79.375]},{"type":"Long","lane":6,"time":78.75},{"type":"Sim","lane":[2,6],"time":78.75},{"type":"Long","lane":2,"time":79.375},{"type":"Long","lane":6,"time":79.375},{"type":"Sim","lane":[2,6],"time":79.375},{"type":"Single","lane":3,"time":80},{"type":"Single","lane":7,"time":80.3125},{"type":"Single","lane":3,"time":80.625},{"type":"Single","lane":6,"time":81.25},{"type":"Single","lane":2,"time":81.5625},{"type":"Single","lane":6,"time":81.875},{"type":"Single","lane":5,"time":82.5},{"type":"Single","lane":5,"time":82.8125},{"type":"Single","lane":5,"time":83.125},{"type":"Single","lane":2,"time":83.75},{"type":"Single","lane":6,"time":84.0625},{"type":"Single","lane":2,"time":84.375},{"type":"Single","lane":6,"time":84.6875},{"type":"Single","lane":4,"time":85},{"type":"Single","lane":1,"time":85},{"type":"Sim","lane":[1,4],"time":85},{"type":"Single","lane":6,"time":85.625},{"type":"Single","lane":3,"time":85.9375},{"type":"Single","lane":2,"time":86.25},{"type":"Single","lane":5,"time":86.25},{"type":"Sim","lane":[2,5],"time":86.25},{"type":"Single","lane":7,"time":86.875},{"type":"Single","lane":2,"time":87.1875},{"type":"Bar","lane":[7,7],"time":[87.5,87.8125]},{"type":"Long","lane":7,"time":87.5},{"type":"Long","lane":7,"time":87.8125},{"type":"Single","lane":3,"time":88.125},{"type":"Bar","lane":[1,1],"time":[88.75,89.0625]},{"type":"Long","lane":1,"time":88.75},{"type":"Long","lane":1,"time":89.0625},{"type":"Single","lane":6,"time":89.375},{"type":"Single","lane":5,"time":90},{"type":"Single","lane":1,"time":90},{"type":"Sim","lane":[1,5],"time":90},{"type":"Skill","lane":6,"time":90.625},{"type":"Single","lane":2,"time":91.25},{"type":"Single","lane":6,"time":91.5625},{"type":"Single","lane":2,"time":91.875},{"type":"Single","lane":5,"time":92.5},{"type":"Single","lane":1,"time":92.5},{"type":"Sim","lane":[1,5],"time":92.5},{"type":"Single","lane":5,"time":93.125},{"type":"Single","lane":6,"time":93.75},{"type":"Single","lane":2,"time":94.0625},{"type":"Single","lane":7,"time":94.375},{"type":"Single","lane":2,"time":94.6875},{"type":"Bar","lane":[6,6],"time":[95,95.625]},{"type":"Long","lane":6,"time":95},{"type":"Long","lane":6,"time":95.625},{"type":"Bar","lane":[3,3],"time":[96.25,96.875]},{"type":"Long","lane":3,"time":96.25},{"type":"Long","lane":3,"time":96.875},{"type":"Bar","lane":[2,2],"time":[97.5,98.75]},{"type":"Long","lane":2,"time":97.5},{"type":"Bar","lane":[6,6],"time":[97.5,98.75]},{"type":"Long","lane":6,"time":97.5},{"type":"Sim","lane":[2,6],"time":97.5},{"type":"Long","lane":2,"time":98.75},{"type":"Long","lane":6,"time":98.75},{"type":"Sim","lane":[2,6],"time":98.75},{"type":"SingleOff","lane":2,"time":99.21875},{"type":"SingleOff","lane":6,"time":99.21875},{"type":"Sim","lane":[2,6],"time":99.21875},{"type":"SingleOff","lane":2,"time":99.53125},{"type":"SingleOff","lane":6,"time":99.53125},{"type":"Sim","lane":[2,6],"time":99.53125},{"type":"Bar","lane":[3,3],"time":[99.84375,100.3125]},{"type":"Long","lane":3,"time":99.84375},{"type":"Long","lane":3,"time":100.3125},{"type":"Single","lane":6,"time":100.3125},{"type":"Sim","lane":[3,6],"time":100.3125},{"type":"Single","lane":3,"time":100.625},{"type":"Bar","lane":[7,7],"time":[101.09375,101.5625]},{"type":"Long","lane":7,"time":101.09375},{"type":"Long","lane":7,"time":101.5625},{"type":"Single","lane":4,"time":101.5625},{"type":"Sim","lane":[4,7],"time":101.5625},{"type":"Single","lane":7,"time":101.875},{"type":"Bar","lane":[1,1],"time":[102.34375,102.8125]},{"type":"Long","lane":1,"time":102.34375},{"type":"Long","lane":1,"time":102.8125},{"type":"Single","lane":4,"time":102.8125},{"type":"Sim","lane":[1,4],"time":102.8125},{"type":"Single","lane":1,"time":103.125},{"type":"Bar","lane":[6,6],"time":[103.59375,104.0625]},{"type":"Long","lane":6,"time":103.59375},{"type":"Long","lane":6,"time":104.0625},{"type":"Single","lane":3,"time":104.0625},{"type":"Sim","lane":[3,6],"time":104.0625},{"type":"Single","lane":2,"time":104.375},{"type":"Single","lane":5,"time":104.375},{"type":"Sim","lane":[2,5],"time":104.375},{"type":"Skill","lane":7,"time":105},{"type":"Bar","lane":[7,7],"time":[105,105.46875]},{"type":"Bar","lane":[1,1],"time":[105,105.46875]},{"type":"Long","lane":1,"time":105},{"type":"Sim","lane":[1,7],"time":105},{"type":"Long","lane":1,"time":105.46875},{"type":"Long","lane":7,"time":105.46875},{"type":"Sim","lane":[1,7],"time":105.46875},{"type":"Bar","lane":[2,2],"time":[105.9375,106.875]},{"type":"Long","lane":2,"time":105.9375},{"type":"Bar","lane":[6,6],"time":[105.9375,106.875]},{"type":"Long","lane":6,"time":105.9375},{"type":"Sim","lane":[2,6],"time":105.9375},{"type":"Long","lane":2,"time":106.875},{"type":"Long","lane":6,"time":106.875},{"type":"Sim","lane":[2,6],"time":106.875},{"type":"Bar","lane":[3,3],"time":[107.34375,108.59375]},{"type":"Long","lane":3,"time":107.34375},{"type":"Bar","lane":[5,5],"time":[107.34375,108.59375]},{"type":"Long","lane":5,"time":107.34375},{"type":"Sim","lane":[3,5],"time":107.34375},{"type":"Long","lane":3,"time":108.59375},{"type":"Long","lane":5,"time":108.59375},{"type":"Sim","lane":[3,5],"time":108.59375},{"type":"SingleOff","lane":2,"time":109.53125},{"type":"SingleOff","lane":6,"time":109.53125},{"type":"Sim","lane":[2,6],"time":109.53125},{"type":"Single","lane":2,"time":110},{"type":"Single","lane":6,"time":110.625},{"type":"SingleOff","lane":3,"time":111.09375},{"type":"SingleOff","lane":5,"time":111.40625},{"type":"SingleOff","lane":3,"time":111.71875},{"type":"SingleOff","lane":3,"time":112.03125},{"type":"SingleOff","lane":5,"time":112.03125},{"type":"Sim","lane":[3,5],"time":112.03125},{"type":"Single","lane":2,"time":112.5},{"type":"Bar","lane":[7,7],"time":[112.5,114.6875]},{"type":"Long","lane":7,"time":112.5},{"type":"Sim","lane":[2,7],"time":112.5},{"type":"Long","lane":7,"time":114.6875},{"type":"Single","lane":5,"time":115},{"type":"Bar","lane":[2,2],"time":[115,116.875]},{"type":"Long","lane":2,"time":115},{"type":"Sim","lane":[2,5],"time":115},{"type":"Long","lane":2,"time":116.875},{"type":"SingleOff","lane":2,"time":117.34375},{"type":"SingleOff","lane":6,"time":117.34375},{"type":"Sim","lane":[2,6],"time":117.34375},{"type":"Single","lane":2,"time":117.8125},{"type":"Single","lane":6,"time":117.8125},{"type":"Sim","lane":[2,6],"time":117.8125}]